<Properties StartupConfiguration="{31CEA5A7-D444-48FA-BA4C-6D7330C638B8}|Default">
  <MonoDevelop.Ide.ItemProperties.ElephantReferenceExercise PreferredExecutionTarget="MonoDevelop.Default" />
  <MonoDevelop.Ide.Workbench ActiveDocument="ElephantReferenceExercise/Program.cs">
    <Files>
      <File FileName="ElephantReferenceExercise/Program.cs" Line="56" Column="1" />
      <File FileName="ElephantReferenceExercise/Elephant.cs" Line="28" Column="1" />
    </Files>
    <Pads>
      <Pad Id="ProjectPad">
        <State name="__root__">
          <Node name="ElephantReferenceExercise" expanded="True">
            <Node name="ElephantReferenceExercise" expanded="True">
              <Node name="Program.cs" selected="True" />
            </Node>
          </Node>
        </State>
      </Pad>
      <Pad Id="MonoDevelop.Debugger.WatchPad">
        <State>
          <Value>Name</Value>
        </State>
      </Pad>
    </Pads>
  </MonoDevelop.Ide.Workbench>
  <MonoDevelop.Ide.DebuggingService.PinnedWatches />
  <MonoDevelop.Ide.Workspace ActiveConfiguration="Debug" />
  <MonoDevelop.Ide.DebuggingService.Breakpoints>
    <BreakpointStore>
      <Breakpoint file="/Users/daisukehashimoto/Documents/Programming/C#/Books/Head First C#/Chapter 4/ElephantReferenceExercise/ElephantReferenceExercise/Elephant.cs" relfile="ElephantReferenceExercise/Elephant.cs" line="27" column="1" />
    </BreakpointStore>
  </MonoDevelop.Ide.DebuggingService.Breakpoints>
  <MultiItemStartupConfigurations />
</Properties>